2° Periodo/AC_1/Guias/Guia 09/Verilog/clock.v
module clock ( output clk ); 
    reg clk;
    
    initial begin : start
    clk = 1'b0; 
    end

    always begin : clock 
        #12 clk = ~clk; 
    end 
endmodule

2° Periodo/AC_1/Guias/Guia 09/Verilog/Guia_0904.v
// Guia 08 
// 801779 
// Giuseppe

`include "clock.v" 

module pulse ( signal, clock ); 
    input  clock; 
    output signal; 
    reg    signal; 
    
    always @ ( posedge clock ) 
    begin : pulse
        signal = 1'b1;
        #2  signal = 1'b0; 
        #2  signal = 1'b1; 
        #2  signal = 1'b0;
        #2  signal = 1'b1;
        #2  signal = 1'b0;
    end 
endmodule 

module Guia_0904; 
    wire  clock; 
    clock clk ( clock ); 
    
    wire  p1; 
    pulse pls1 ( p1, clock ); 
    
    initial begin : main 
        $dumpfile ( "Guia_0904.vcd" ); 
        $dumpvars ( 1, clock, p1 ); 
        
        #480 $finish; 
    end 
endmodule

2° Periodo/AC_1/Guias/Guia 09/Verilog/Guia_0904.vcd
$date
	Sun Sep 29 19:22:04 2024
$end
$version
	Icarus Verilog
$end
$timescale
	1s
$end
$scope module Guia_0904 $end
$var wire 1 ! clock $end
$upscope $end
$scope module Guia_0904 $end
$var wire 1 " p1 $end
$upscope $end
$enddefinitions $end
$comment Show the parameter values. $end
$dumpall
$end
#0
$dumpvars
x"
0!
$end
#12
1"
1!
#14
0"
#16
1"
#18
0"
#20
1"
#22
0"
#24
0!
#36
1"
1!
#38
0"
#40
1"
#42
0"
#44
1"
#46
0"
#48
0!
#60
1"
1!
#62
0"
#64
1"
#66
0"
#68
1"
#70
0"
#72
0!
#84
1"
1!
#86
0"
#88
1"
#90
0"
#92
1"
#94
0"
#96
0!
#108
1"
1!
#110
0"
#112
1"
#114
0"
#116
1"
#118
0"
#120
0!
#132
1"
1!
#134
0"
#136
1"
#138
0"
#140
1"
#142
0"
#144
0!
#156
1"
1!
#158
0"
#160
1"
#162
0"
#164
1"
#166
0"
#168
0!
#180
1"
1!
#182
0"
#184
1"
#186
0"
#188
1"
#190
0"
#192
0!
#204
1"
1!
#206
0"
#208
1"
#210
0"
#212
1"
#214
0"
#216
0!
#228
1"
1!
#230
0"
#232
1"
#234
0"
#236
1"
#238
0"
#240
0!
#252
1"
1!
#254
0"
#256
1"
#258
0"
#260
1"
#262
0"
#264
0!
#276
1"
1!
#278
0"
#280
1"
#282
0"
#284
1"
#286
0"
#288
0!
#300
1"
1!
#302
0"
#304
1"
#306
0"
#308
1"
#310
0"
#312
0!
#324
1"
1!
#326
0"
#328
1"
#330
0"
#332
1"
#334
0"
#336
0!
#348
1"
1!
#350
0"
#352
1"
#354
0"
#356
1"
#358
0"
#360
0!
#372
1"
1!
#374
0"
#376
1"
#378
0"
#380
1"
#382
0"
#384
0!
#396
1"
1!
#398
0"
#400
1"
#402
0"
#404
1"
#406
0"
#408
0!
#420
1"
1!
#422
0"
#424
1"
#426
0"
#428
1"
#430
0"
#432
0!
#444
1"
1!
#446
0"
#448
1"
#450
0"
#452
1"
#454
0"
#456
0!
#468
1"
1!
#470
0"
#472
1"
#474
0"
#476
1"
#478
0"
